pokdeng/__init__.py
pokdeng/card.py
pokdeng/cardholder.py
pokdeng/exception.py
pokdeng/game.py
pokdeng/hand.py
pokdeng/idgenerator.py
pokdeng/pocket.py
pokdeng-0.0.3.dist-info/LICENSE
pokdeng-0.0.3.dist-info/METADATA
pokdeng-0.0.3.dist-info/WHEEL
pokdeng-0.0.3.dist-info/top_level.txt
pokdeng-0.0.3.dist-info/RECORD
